pydiscotool/__init__.py
pydiscotool/create_tfrecords_from_csv.py
pydiscotool/init.py
pydiscotool/tfrecords_creator.py
pydiscotools/__init__.py
pydiscotools/tfrecords_creator.py
pydiscotools-0.1.3.dist-info/LICENSE.txt
pydiscotools-0.1.3.dist-info/METADATA
pydiscotools-0.1.3.dist-info/WHEEL
pydiscotools-0.1.3.dist-info/top_level.txt
pydiscotools-0.1.3.dist-info/RECORD
