Metadata-Version: 2.1
Name: pydiscotools
Version: 0.1.3
Summary: A suite of python tools to help with Disco
Home-page: https://github.com/Wundr-Disco/pydiscotools
Author: Daniel Carrera
Author-email: daniel.r.carrera@outlook.com
License: UNKNOWN
Platform: UNKNOWN
Classifier: Programming Language :: Python :: 3
Classifier: License :: OSI Approved :: MIT License
Classifier: Operating System :: OS Independent
Requires-Dist: tensorflow
Requires-Dist: pandas
